netshow_linux_lib-1.1.5-py2.7-nspkg.pth
netshowlib/linux/_version.py
netshowlib/linux/ip_neighbor.py
netshowlib/linux/ip_address.py
netshowlib/linux/lldp.py
netshowlib/linux/provider_discovery.py
netshowlib/linux/common.py
netshowlib/linux/lacp.py
netshowlib/linux/cache.py
netshowlib/linux/bridge.py
netshowlib/linux/bond.py
netshowlib/linux/system_summary.py
netshowlib/linux/iface.py
netshow_linux_lib-1.1.5.data/data/share/netshow-lib/providers/linux
netshow_linux_lib-1.1.5.data/data/share/locale/en/LC_MESSAGES/netshow-linux-lib.mo
netshow/linux/print_bridge.py
netshow/linux/print_bond.py
netshow/linux/show_interfaces.py
netshow/linux/netjson_encoder.py
netshow/linux/show.py
netshow/linux/show_system.py
netshow/linux/common.py
netshow/linux/show_neighbors.py
netshow/linux/print_iface.py
netshow_linux_lib-1.1.5.dist-info/METADATA
netshow_linux_lib-1.1.5.dist-info/RECORD
netshow_linux_lib-1.1.5.dist-info/metadata.json
netshow_linux_lib-1.1.5.dist-info/WHEEL
netshow_linux_lib-1.1.5.dist-info/DESCRIPTION.rst
netshow_linux_lib-1.1.5.dist-info/namespace_packages.txt
netshow_linux_lib-1.1.5.dist-info/top_level.txt
