Metadata-Version: 2.0
Name: netshow-linux-lib
Version: 1.1.5
Summary: Netshow Provider for Linux Operating Systems
Home-page: http://github.com/CumulusNetworks/netshow-linux-lib
Author: Cumulus Networks
Author-email: ce-ceng@cumulusnetworks.com
License: GPLv2
Platform: UNKNOWN
Classifier: License :: OSI Approved :: GNU General Public License v2 (GPLv2)
Classifier: Development Status :: 4 - Beta
Classifier: Topic :: System :: Networking
Classifier: Intended Audience :: Developers
Classifier: Intended Audience :: System Administrators
Classifier: Operating System :: POSIX :: Linux
Requires-Dist: setuptools
Requires-Dist: netshow-core-lib
Requires-Dist: netshow-core
Requires-Dist: network-docopt
Requires-Dist: tabulate
Requires-Dist: inflection
